LICENSE
MANIFEST.in
README.md
setup.py
elfcall/__init__.py
elfcall/logger.py
elfcall/version.py
elfcall.egg-info/PKG-INFO
elfcall.egg-info/SOURCES.txt
elfcall.egg-info/dependency_links.txt
elfcall.egg-info/entry_points.txt
elfcall.egg-info/not-zip-safe
elfcall.egg-info/requires.txt
elfcall.egg-info/top_level.txt
elfcall/client/__init__.py
elfcall/client/gen.py
elfcall/client/shell.py
elfcall/client/tree.py
elfcall/main/__init__.py
elfcall/main/client.py
elfcall/main/elf.py
elfcall/main/ld.py
elfcall/main/graph/__init__.py
elfcall/main/graph/base.py
elfcall/main/graph/cypher.py
elfcall/main/graph/dot.py
elfcall/main/graph/gexf.py
elfcall/main/graph/text.py
elfcall/utils/__init__.py
elfcall/utils/fileio.py
elfcall/utils/terminal.py