Metadata-Version: 2.1
Name: elfcall
Version: 0.0.0
Summary: generate callgraph data for ELF binaries
Home-page: https://github.com/vsoch/elfcall
Author: Vanessa Sochat
Author-email: vsoch@users.noreply.github.io
Maintainer: Vanessa Sochat
License: LICENSE
Keywords: ELF,callgraph
Platform: UNKNOWN
Classifier: Intended Audience :: Science/Research
Classifier: Intended Audience :: Developers
Classifier: License :: OSI Approved :: Mozilla Public License 2.0 (MPL 2.0)
Classifier: Programming Language :: C
Classifier: Programming Language :: Python
Classifier: Topic :: Software Development
Classifier: Topic :: Scientific/Engineering
Classifier: Operating System :: Unix
Classifier: Programming Language :: Python :: 3.3
Provides-Extra: all
